pivvo/__init__.py
pivvo/cli.py
pivvo/main.py
pivvo-0.1.1.dist-info/licenses/LICENSE
pivvo-0.1.1.dist-info/METADATA
pivvo-0.1.1.dist-info/WHEEL
pivvo-0.1.1.dist-info/entry_points.txt
pivvo-0.1.1.dist-info/top_level.txt
pivvo-0.1.1.dist-info/RECORD
