Metadata-Version: 2.4
Name: pivvo
Version: 0.1.1
Summary: CLI tool to auto-init Python projects with venv, git, and basic files.
Author-email: Devrat Kuntal <rdxdevbhai76@gmail.com>
License-Expression: MIT
Keywords: cli,project,automation,python
Classifier: Programming Language :: Python :: 3.10
Classifier: Programming Language :: Python :: 3.11
Classifier: Programming Language :: Python :: 3.12
Classifier: Operating System :: OS Independent
Requires-Python: >=3.10
License-File: LICENSE
Requires-Dist: typer
Requires-Dist: rich
Requires-Dist: GitPython
Requires-Dist: pyfiglet
Provides-Extra: dev
Requires-Dist: pytest; extra == "dev"
Dynamic: license-file
